drf_serializer_cache/__init__.py
drf_serializer_cache/cache.py
tests/app/__init__.py
tests/app/apps.py
tests/app/models.py
tests/app/serializers.py
tests/functional/__init__.py
tests/functional/test_model_serializer.py
tests/functional/test_serializer.py
tests/performance/__init__.py
tests/performance/list_simple.py
tests/performance/list_with_reused_instance.py
tests/performance/recursive_model_serializer.py
drf_serializer_cache-0.3.4.dist-info/LICENSE
drf_serializer_cache-0.3.4.dist-info/METADATA
drf_serializer_cache-0.3.4.dist-info/WHEEL
drf_serializer_cache-0.3.4.dist-info/top_level.txt
drf_serializer_cache-0.3.4.dist-info/RECORD
