Metadata-Version: 2.1
Name: drf-serializer-cache
Version: 0.3.4
Summary: Django REST framework (DRF) serializer speedup
Home-page: https://github.com/K0Te/drf-serializer-cache
License: BSD
Project-URL: Bug Reports, https://github.com/K0Te/drf-serializer-cache/issues
Project-URL: Source, https://github.com/K0Te/drf-serializer-cache
Keywords: drf cache performance
Platform: UNKNOWN
Classifier: Development Status :: 4 - Beta
Classifier: Intended Audience :: Developers
Classifier: Framework :: Django
Classifier: License :: OSI Approved :: BSD License
Classifier: Programming Language :: Python :: 3
Classifier: Programming Language :: Python :: 3.4
Classifier: Programming Language :: Python :: 3.5
Classifier: Programming Language :: Python :: 3.6
Requires-Dist: django
Requires-Dist: djangorestframework
